README.md
setup.py
allow/__init__.py
allow/config.py
allow/run.py
allow/server.py
allow.egg-info/PKG-INFO
allow.egg-info/SOURCES.txt
allow.egg-info/dependency_links.txt
allow.egg-info/entry_points.txt
allow.egg-info/requires.txt
allow.egg-info/top_level.txt